pydmsoft/__init__.py
pydmsoft/dm.py
pydmsoft-1.0.1.dist-info/METADATA
pydmsoft-1.0.1.dist-info/WHEEL
pydmsoft-1.0.1.dist-info/top_level.txt
pydmsoft-1.0.1.dist-info/RECORD
