Metadata-Version: 2.1
Name: pydmsoft
Version: 1.0.1
Summary: A Simple python Wrapper for DM
Home-page: https://github.com/130347665/PyDmSoft
Author: Relaxing
Author-email: bneson901203@yahoo.com.tw
License: UNKNOWN
Platform: UNKNOWN
Classifier: Programming Language :: Python :: 3
Classifier: License :: OSI Approved :: MIT License
Classifier: Operating System :: OS Independent
Requires-Python: >=3.6
Requires-Dist: comtypes
Requires-Dist: pywin32
